strangeworks/annealing/__init__.py
strangeworks/annealing/problem.py
strangeworks/annealing/sampler.py
strangeworks/annealing/solver.py
strangeworks_annealing-0.1.5.dist-info/LICENSE
strangeworks_annealing-0.1.5.dist-info/WHEEL
strangeworks_annealing-0.1.5.dist-info/METADATA
strangeworks_annealing-0.1.5.dist-info/RECORD
