Metadata-Version: 2.1
Name: strangeworks-annealing
Version: 0.1.5
Summary: Strangeworks Annealing SDK extension
License: Apache-2.0
Author: Strange Devs
Author-email: hello@strangeworks.com
Requires-Python: >=3.8,<4.0
Classifier: License :: OSI Approved :: Apache Software License
Classifier: Programming Language :: Python :: 3
Classifier: Programming Language :: Python :: 3.10
Classifier: Programming Language :: Python :: 3.8
Classifier: Programming Language :: Python :: 3.9
Requires-Dist: dwave-embedding-utilities (>=0.3.0,<0.4.0)
Requires-Dist: minorminer (>=0.2.7,<0.3.0)
Requires-Dist: networkx (>=2.6.3,<3.0.0)
Requires-Dist: strangeworks (>=0.2.6,<0.3.0)
